taskr/__init__.py
taskr/__version__.py
taskr/cli.py
taskr/runners.py
taskr/script_template.py
taskr/taskr.py
taskr/template.py
taskr/utils.py
taskr_cli-1.2.9.dist-info/METADATA
taskr_cli-1.2.9.dist-info/WHEEL
taskr_cli-1.2.9.dist-info/entry_points.txt
taskr_cli-1.2.9.dist-info/licenses/LICENSE
taskr_cli-1.2.9.dist-info/RECORD
