Metadata-Version: 2.1
Name: taskr_cli
Version: 1.2.9
Summary: A language agnostic make-like tool meant for python projects
Keywords: cli,utility
Author-Email: Kyle Peasley <Kyle.Peasley@gmail.com>
License: MIT License
Classifier: Environment :: Console
Classifier: Programming Language :: Python :: 3
Project-URL: Homepage, https://gitlab.com/peasleyk/taskr
Project-URL: Repository, https://gitlab.com/peasleyk/taskr
Project-URL: Documentation, https://gitlab.com/peasleyk/taskr
Requires-Python: >3.8
Provides-Extra: dev
Requires-Dist: build; extra == "dev"
Requires-Dist: mypy; extra == "dev"
Requires-Dist: pytest; extra == "dev"
Requires-Dist: ruff; extra == "dev"
Requires-Dist: twine; extra == "dev"
